Metadata-Version: 2.4
Name: copulas
Version: 0.14.0
Summary: Create tabular synthetic data using copulas-based modeling.
Author-email: "DataCebo, Inc." <info@sdv.dev>
License: BSL-1.1
Project-URL: Source Code, https://github.com/sdv-dev/Copulas/
Project-URL: Issue Tracker, https://github.com/sdv-dev/Copulas/issues
Project-URL: Changes, https://github.com/sdv-dev/Copulas/blob/main/HISTORY.md
Project-URL: Twitter, https://twitter.com/sdv_dev
Project-URL: Chat, https://bit.ly/sdv-slack-invite
Keywords: copulas
Classifier: Development Status :: 2 - Pre-Alpha
Classifier: Intended Audience :: Developers
Classifier: License :: Free for non-commercial use
Classifier: Natural Language :: English
Classifier: Programming Language :: Python :: 3
Classifier: Programming Language :: Python :: 3.9
Classifier: Programming Language :: Python :: 3.10
Classifier: Programming Language :: Python :: 3.11
Classifier: Programming Language :: Python :: 3.12
Classifier: Programming Language :: Python :: 3.13
Classifier: Programming Language :: Python :: 3.14
Classifier: Topic :: Scientific/Engineering :: Artificial Intelligence
Requires-Python: <3.15,>=3.9
License-File: LICENSE
Requires-Dist: numpy>=1.21.0; python_version < "3.10"
Requires-Dist: numpy>=1.23.3; python_version >= "3.10" and python_version < "3.12"
Requires-Dist: numpy>=1.26.0; python_version >= "3.12" and python_version < "3.13"
Requires-Dist: numpy>=2.1.0; python_version >= "3.13" and python_version < "3.14"
Requires-Dist: numpy>=2.3.2; python_version >= "3.14"
Requires-Dist: pandas>=1.4.0; python_version < "3.11"
Requires-Dist: pandas>=1.5.0; python_version >= "3.11" and python_version < "3.12"
Requires-Dist: pandas>=2.1.1; python_version >= "3.12" and python_version < "3.13"
Requires-Dist: pandas>=2.2.3; python_version >= "3.13" and python_version < "3.14"
Requires-Dist: pandas>=2.3.3; python_version >= "3.14"
Requires-Dist: plotly>=5.10.0; python_version < "3.13"
Requires-Dist: plotly>=5.12.0; python_version >= "3.13"
Requires-Dist: scipy>=1.7.3; python_version < "3.10"
Requires-Dist: scipy>=1.9.2; python_version >= "3.10" and python_version < "3.12"
Requires-Dist: scipy>=1.12.0; python_version >= "3.12" and python_version < "3.13"
Requires-Dist: scipy>=1.14.1; python_version >= "3.13" and python_version < "3.14"
Requires-Dist: scipy>=1.16.1; python_version >= "3.14"
Provides-Extra: tutorials
Requires-Dist: markupsafe>=2.0.1; extra == "tutorials"
Requires-Dist: scikit-learn>=0.24; python_version < "3.12" and extra == "tutorials"
Requires-Dist: scikit-learn>=1.3.1; python_version >= "3.12" and extra == "tutorials"
Requires-Dist: jupyter>=1.0.0; extra == "tutorials"
Provides-Extra: test
Requires-Dist: copulas[tutorials]; extra == "test"
Requires-Dist: pytest>=6.2.5; extra == "test"
Requires-Dist: pytest-cov>=2.6.0; extra == "test"
Requires-Dist: pytest-rerunfailures>=10.3; extra == "test"
Requires-Dist: tomli>=2.0.0; extra == "test"
Provides-Extra: dev
Requires-Dist: copulas[test,tutorials]; extra == "dev"
Requires-Dist: pip>=9.0.1; extra == "dev"
Requires-Dist: build>=1.0.0; extra == "dev"
Requires-Dist: bump-my-version>=0.18.3; extra == "dev"
Requires-Dist: watchdog>=1.0.1; extra == "dev"
Requires-Dist: nbsphinx<0.10,>=0.9.7; extra == "dev"
Requires-Dist: Sphinx<7.5,>=7.4.7; extra == "dev"
Requires-Dist: sphinx_rtd_theme<3.1,>=3.0.2; extra == "dev"
Requires-Dist: sphinxcontrib_applehelp<2.1,>=2.0.0; extra == "dev"
Requires-Dist: sphinxcontrib-devhelp<2.1,>=2.0.0; extra == "dev"
Requires-Dist: sphinxcontrib-htmlhelp<2.2,>=2.1.0; extra == "dev"
Requires-Dist: sphinxcontrib_serializinghtml<2.1,>=2.0.0; extra == "dev"
Requires-Dist: sphinxcontrib_qthelp<2.1,>=2.0.0; extra == "dev"
Requires-Dist: alabaster<0.8,>=0.7.16; extra == "dev"
Requires-Dist: lxml-html-clean<0.5,>=0.4.1; extra == "dev"
Requires-Dist: Jinja2<3.2,>=3.1.6; extra == "dev"
Requires-Dist: myst_parser<4.1,>=3.0.1; extra == "dev"
Requires-Dist: ruff<1,>=0.3.2; extra == "dev"
Requires-Dist: twine>=1.10.0; extra == "dev"
Requires-Dist: wheel>=0.30.0; extra == "dev"
Requires-Dist: coverage<7.8,>=7.7.1; extra == "dev"
Requires-Dist: invoke; extra == "dev"
Requires-Dist: urllib3<2.4,>=1.26.20; extra == "dev"
Requires-Dist: tabulate<0.10,>=0.9.0; extra == "dev"
Requires-Dist: boto3<1.38,>=1.37.18; extra == "dev"
Requires-Dist: docutils<0.22,>=0.21.2; extra == "dev"
Provides-Extra: readme
Requires-Dist: rundoc<0.5,>=0.4.3; extra == "readme"
Dynamic: license-file
